neato/__init__.py
neato/activations.py
neato/ecosystem.py
neato/genome.py
neato-1.0.0.dist-info/LICENSE
neato-1.0.0.dist-info/METADATA
neato-1.0.0.dist-info/WHEEL
neato-1.0.0.dist-info/top_level.txt
neato-1.0.0.dist-info/RECORD
