Metadata-Version: 2.1
Name: neato
Version: 1.0.0
Summary: An implementation of NEAT (NeuroEvolution of Augmenting Topologies) by Kenneth O. Stanley
Home-page: https://github.com/sephpace/neato
Author: Seph (Joseph) Pace
Author-email: sephpace@gmail.com
License: MIT
Project-URL: Bug Tracker, https://github.com/sephpace/neato/issues
Platform: UNKNOWN
Classifier: Programming Language :: Python :: 3
Classifier: License :: OSI Approved :: MIT License
Classifier: Operating System :: OS Independent
Requires-Python: >=3.7
Requires-Dist: numpy
